{"title":"0x01位运算--64位整数乘法","uid":"97612da9b20c890887f4d716902dc0f2","slug":"0x01位运算-64位整数乘法","date":"2022-04-14T04:58:43.000Z","updated":"2022-04-14T05:11:44.147Z","comments":true,"path":"api/articles/0x01位运算-64位整数乘法.json","keywords":null,"cover":[],"content":"<h2 id=\"0x01-位运算——64位整数乘法\"><a href=\"#0x01-位运算——64位整数乘法\" class=\"headerlink\" title=\"0x01 位运算——64位整数乘法\"></a>0x01 位运算——64位整数乘法</h2><p><img src=\"https://img-blog.csdnimg.cn/ab445f6ed60840cc9d5b2750f575a6d0.png?x-oss-process=image/watermark,type_d3F5LXplbmhlaQ,shadow_50,text_Q1NETiBAdGltZXJfY2F0Y2g=,size_20,color_FFFFFF,t_70,g_se,x_16\" alt=\"在这里插入图片描述\"></p>\n<ul>\n<li>问题简析<blockquote><span class=\"custom-blockquote-svg\"><svg width=\"24\" height=\"24\" viewBox=\"0 0 24 24\" fill=\"\" xmlns=\"http://www.w3.org/2000/svg\" data-reactroot=\"\">\n<path fill=\"\" d=\"M22 12C22 6.5 17.5 2 12 2C6.5 2 2 6.5 2 12C2 17.5 6.5 22 12 22C13.8 22 15.5 21.5 17 20.6L22 22L20.7 17C21.5 15.5 22 13.8 22 12Z\" undefined=\"1\"></path>\n<path fill=\"\" d=\"M15.97 11.5H16.04C17.12 11.5 18 12.38 18 13.47V13.53C18 14.62 17.12 15.5 16.03 15.5H15.96C14.88 15.5 14 14.62 14 13.53V13.46C14 12.38 14.88 11.5 15.97 11.5Z\" undefined=\"1\"></path>\n<path fill=\"\" d=\"M7.97 11.5H8.04C9.12 11.5 10 12.38 10 13.47V13.53C10 14.62 9.12 15.5 8.03 15.5H7.97C6.88 15.5 6 14.62 6 13.53V13.46C6 12.38 6.88 11.5 7.97 11.5Z\" undefined=\"1\"></path>\n<path stroke-linejoin=\"round\" stroke-linecap=\"round\" stroke-miterlimit=\"10\" stroke-width=\"2\" stroke=\"\" d=\"M17 8.5C15.23 8.97 14.07 10.84 14.01 13.27C14 13.33 14 13.4 14 13.47V13.5\"></path>\n<path stroke-linejoin=\"round\" stroke-linecap=\"round\" stroke-miterlimit=\"10\" stroke-width=\"2\" stroke=\"\" d=\"M9 8.5C7.23 8.97 6.07 10.84 6.01 13.27C6 13.33 6 13.4 6 13.47V13.5\"></path>\n<path stroke-linejoin=\"round\" stroke-linecap=\"round\" stroke-miterlimit=\"10\" stroke-width=\"2\" stroke=\"\" d=\"M15.97 11.5H16.04C17.12 11.5 18 12.38 18 13.47V13.53C18 14.62 17.12 15.5 16.03 15.5H15.96C14.88 15.5 14 14.62 14 13.53V13.46C14 12.38 14.88 11.5 15.97 11.5Z\"></path>\n<path stroke-linejoin=\"round\" stroke-linecap=\"round\" stroke-miterlimit=\"10\" stroke-width=\"2\" stroke=\"\" d=\"M7.97 11.5H8.04C9.12 11.5 10 12.38 10 13.47V13.53C10 14.62 9.12 15.5 8.03 15.5H7.97C6.88 15.5 6 14.62 6 13.53V13.46C6 12.38 6.88 11.5 7.97 11.5Z\"></path>\n</svg>\n</span><p>C++内置的最高整数类型是64位，所以显然不能通过直接运算得到答案，我们需要一些特殊的处理方法，在这里提供两种方法。</p></blockquote>\n</li>\n</ul>\n<ol>\n<li>思路一</li>\n</ol>\n<blockquote><span class=\"custom-blockquote-svg\"><svg width=\"24\" height=\"24\" viewBox=\"0 0 24 24\" fill=\"\" xmlns=\"http://www.w3.org/2000/svg\" data-reactroot=\"\">\n<path fill=\"\" d=\"M22 12C22 6.5 17.5 2 12 2C6.5 2 2 6.5 2 12C2 17.5 6.5 22 12 22C13.8 22 15.5 21.5 17 20.6L22 22L20.7 17C21.5 15.5 22 13.8 22 12Z\" undefined=\"1\"></path>\n<path fill=\"\" d=\"M15.97 11.5H16.04C17.12 11.5 18 12.38 18 13.47V13.53C18 14.62 17.12 15.5 16.03 15.5H15.96C14.88 15.5 14 14.62 14 13.53V13.46C14 12.38 14.88 11.5 15.97 11.5Z\" undefined=\"1\"></path>\n<path fill=\"\" d=\"M7.97 11.5H8.04C9.12 11.5 10 12.38 10 13.47V13.53C10 14.62 9.12 15.5 8.03 15.5H7.97C6.88 15.5 6 14.62 6 13.53V13.46C6 12.38 6.88 11.5 7.97 11.5Z\" undefined=\"1\"></path>\n<path stroke-linejoin=\"round\" stroke-linecap=\"round\" stroke-miterlimit=\"10\" stroke-width=\"2\" stroke=\"\" d=\"M17 8.5C15.23 8.97 14.07 10.84 14.01 13.27C14 13.33 14 13.4 14 13.47V13.5\"></path>\n<path stroke-linejoin=\"round\" stroke-linecap=\"round\" stroke-miterlimit=\"10\" stroke-width=\"2\" stroke=\"\" d=\"M9 8.5C7.23 8.97 6.07 10.84 6.01 13.27C6 13.33 6 13.4 6 13.47V13.5\"></path>\n<path stroke-linejoin=\"round\" stroke-linecap=\"round\" stroke-miterlimit=\"10\" stroke-width=\"2\" stroke=\"\" d=\"M15.97 11.5H16.04C17.12 11.5 18 12.38 18 13.47V13.53C18 14.62 17.12 15.5 16.03 15.5H15.96C14.88 15.5 14 14.62 14 13.53V13.46C14 12.38 14.88 11.5 15.97 11.5Z\"></path>\n<path stroke-linejoin=\"round\" stroke-linecap=\"round\" stroke-miterlimit=\"10\" stroke-width=\"2\" stroke=\"\" d=\"M7.97 11.5H8.04C9.12 11.5 10 12.38 10 13.47V13.53C10 14.62 9.12 15.5 8.03 15.5H7.97C6.88 15.5 6 14.62 6 13.53V13.46C6 12.38 6.88 11.5 7.97 11.5Z\"></path>\n</svg>\n</span><p>类似于快速幂的思想，把b拆分成k位二进制。<br>$b=C_{k-1}<em>2^{k-1}+C_{k-2}</em>2^{k-2}…+C_{0}<em>2^{0}。<mjx-container class=\"MathJax\" jax=\"SVG\"><svg style=\"vertical-align: 0\" xmlns=\"http://www.w3.org/2000/svg\" width=\"0.036ex\" height=\"0.036ex\" role=\"img\" focusable=\"false\" viewBox=\"0 0 16 16\"><g stroke=\"currentColor\" fill=\"currentColor\" stroke-width=\"0\" transform=\"scale(1,-1)\"><g data-mml-node=\"math\"></g></g></svg></mjx-container>a</em>b=C_{k-1}<em>2^{k-1}</em>a+C_{k-2}<em>2^{k-2}</em>a…+C_{0}<em>2^{0}</em>a。<mjx-container class=\"MathJax\" jax=\"SVG\"><svg style=\"vertical-align: 0\" xmlns=\"http://www.w3.org/2000/svg\" width=\"0.036ex\" height=\"0.036ex\" role=\"img\" focusable=\"false\" viewBox=\"0 0 16 16\"><g stroke=\"currentColor\" fill=\"currentColor\" stroke-width=\"0\" transform=\"scale(1,-1)\"><g data-mml-node=\"math\"></g></g></svg></mjx-container>若算出a<em>b^{i-1}mod~p，则计算(a</em>b^{i-1})<em>2mod~p的过程中不会超过2</em>10^{18}，long ~long可以胜任。$</p>\n<ul>\n<li>时间复杂度分析<br><mjx-container class=\"MathJax\" jax=\"SVG\"><svg style=\"vertical-align: -0.566ex\" xmlns=\"http://www.w3.org/2000/svg\" width=\"30.924ex\" height=\"2.262ex\" role=\"img\" focusable=\"false\" viewBox=\"0 -750 13668.6 1000\"><g stroke=\"currentColor\" fill=\"currentColor\" stroke-width=\"0\" transform=\"scale(1,-1)\"><g data-mml-node=\"math\"><g data-mml-node=\"mi\"><text data-variant=\"italic\" transform=\"scale(1,-1)\" font-size=\"884px\" font-family=\"serif\" font-style=\"italic\">分</text></g><g data-mml-node=\"mi\" transform=\"translate(900,0)\"><text data-variant=\"italic\" transform=\"scale(1,-1)\" font-size=\"884px\" font-family=\"serif\" font-style=\"italic\">解</text></g><g data-mml-node=\"mi\" transform=\"translate(1800,0)\"><text data-variant=\"italic\" transform=\"scale(1,-1)\" font-size=\"884px\" font-family=\"serif\" font-style=\"italic\">出</text></g><g data-mml-node=\"mi\" transform=\"translate(2700,0)\"><text data-variant=\"italic\" transform=\"scale(1,-1)\" font-size=\"884px\" font-family=\"serif\" font-style=\"italic\">的</text></g><g data-mml-node=\"mi\" transform=\"translate(3600,0)\"><text data-variant=\"italic\" transform=\"scale(1,-1)\" font-size=\"884px\" font-family=\"serif\" font-style=\"italic\">项</text></g><g data-mml-node=\"mi\" transform=\"translate(4500,0)\"><text data-variant=\"italic\" transform=\"scale(1,-1)\" font-size=\"884px\" font-family=\"serif\" font-style=\"italic\">数</text></g><g data-mml-node=\"mi\" transform=\"translate(5400,0)\"><text data-variant=\"italic\" transform=\"scale(1,-1)\" font-size=\"884px\" font-family=\"serif\" font-style=\"italic\">为</text></g><g data-mml-node=\"mi\" transform=\"translate(6300,0)\"><path data-c=\"1D458\" d=\"M121 647Q121 657 125 670T137 683Q138 683 209 688T282 694Q294 694 294 686Q294 679 244 477Q194 279 194 272Q213 282 223 291Q247 309 292 354T362 415Q402 442 438 442Q468 442 485 423T503 369Q503 344 496 327T477 302T456 291T438 288Q418 288 406 299T394 328Q394 353 410 369T442 390L458 393Q446 405 434 405H430Q398 402 367 380T294 316T228 255Q230 254 243 252T267 246T293 238T320 224T342 206T359 180T365 147Q365 130 360 106T354 66Q354 26 381 26Q429 26 459 145Q461 153 479 153H483Q499 153 499 144Q499 139 496 130Q455 -11 378 -11Q333 -11 305 15T277 90Q277 108 280 121T283 145Q283 167 269 183T234 206T200 217T182 220H180Q168 178 159 139T145 81T136 44T129 20T122 7T111 -2Q98 -11 83 -11Q66 -11 57 -1T48 16Q48 26 85 176T158 471L195 616Q196 629 188 632T149 637H144Q134 637 131 637T124 640T121 647Z\"></path></g><g data-mml-node=\"mo\" transform=\"translate(7098.8,0)\"><path data-c=\"3D\" d=\"M56 347Q56 360 70 367H707Q722 359 722 347Q722 336 708 328L390 327H72Q56 332 56 347ZM56 153Q56 168 72 173H708Q722 163 722 153Q722 140 707 133H70Q56 140 56 153Z\"></path></g><g data-mml-node=\"mrow\" transform=\"translate(8154.6,0)\"><g data-mml-node=\"mo\"><path data-c=\"2308\" d=\"M174 734Q178 746 190 750H298H369Q400 750 411 747T422 730T411 713T372 709Q365 709 345 709T310 710H214V-235Q206 -248 196 -250Q192 -250 189 -249T184 -247T180 -244T178 -241T176 -237T174 -234V734Z\"></path></g><g data-mml-node=\"mi\" transform=\"translate(444,0)\"><path data-c=\"1D459\" d=\"M117 59Q117 26 142 26Q179 26 205 131Q211 151 215 152Q217 153 225 153H229Q238 153 241 153T246 151T248 144Q247 138 245 128T234 90T214 43T183 6T137 -11Q101 -11 70 11T38 85Q38 97 39 102L104 360Q167 615 167 623Q167 626 166 628T162 632T157 634T149 635T141 636T132 637T122 637Q112 637 109 637T101 638T95 641T94 647Q94 649 96 661Q101 680 107 682T179 688Q194 689 213 690T243 693T254 694Q266 694 266 686Q266 675 193 386T118 83Q118 81 118 75T117 65V59Z\"></path></g><g data-mml-node=\"mi\" transform=\"translate(742,0)\"><path data-c=\"1D45C\" d=\"M201 -11Q126 -11 80 38T34 156Q34 221 64 279T146 380Q222 441 301 441Q333 441 341 440Q354 437 367 433T402 417T438 387T464 338T476 268Q476 161 390 75T201 -11ZM121 120Q121 70 147 48T206 26Q250 26 289 58T351 142Q360 163 374 216T388 308Q388 352 370 375Q346 405 306 405Q243 405 195 347Q158 303 140 230T121 120Z\"></path></g><g data-mml-node=\"msub\" transform=\"translate(1227,0)\"><g data-mml-node=\"mi\"><path data-c=\"1D454\" d=\"M311 43Q296 30 267 15T206 0Q143 0 105 45T66 160Q66 265 143 353T314 442Q361 442 401 394L404 398Q406 401 409 404T418 412T431 419T447 422Q461 422 470 413T480 394Q480 379 423 152T363 -80Q345 -134 286 -169T151 -205Q10 -205 10 -137Q10 -111 28 -91T74 -71Q89 -71 102 -80T116 -111Q116 -121 114 -130T107 -144T99 -154T92 -162L90 -164H91Q101 -167 151 -167Q189 -167 211 -155Q234 -144 254 -122T282 -75Q288 -56 298 -13Q311 35 311 43ZM384 328L380 339Q377 350 375 354T369 368T359 382T346 393T328 402T306 405Q262 405 221 352Q191 313 171 233T151 117Q151 38 213 38Q269 38 323 108L331 118L384 328Z\"></path></g><g data-mml-node=\"TeXAtom\" transform=\"translate(510,-150) scale(0.707)\" data-mjx-texclass=\"ORD\"><g data-mml-node=\"mn\"><path data-c=\"32\" d=\"M109 429Q82 429 66 447T50 491Q50 562 103 614T235 666Q326 666 387 610T449 465Q449 422 429 383T381 315T301 241Q265 210 201 149L142 93L218 92Q375 92 385 97Q392 99 409 186V189H449V186Q448 183 436 95T421 3V0H50V19V31Q50 38 56 46T86 81Q115 113 136 137Q145 147 170 174T204 211T233 244T261 278T284 308T305 340T320 369T333 401T340 431T343 464Q343 527 309 573T212 619Q179 619 154 602T119 569T109 550Q109 549 114 549Q132 549 151 535T170 489Q170 464 154 447T109 429Z\"></path></g></g></g><g data-mml-node=\"mo\" transform=\"translate(2140.6,0)\"><path data-c=\"28\" d=\"M94 250Q94 319 104 381T127 488T164 576T202 643T244 695T277 729T302 750H315H319Q333 750 333 741Q333 738 316 720T275 667T226 581T184 443T167 250T184 58T225 -81T274 -167T316 -220T333 -241Q333 -250 318 -250H315H302L274 -226Q180 -141 137 -14T94 250Z\"></path></g><g data-mml-node=\"mi\" transform=\"translate(2529.6,0)\"><path data-c=\"1D44F\" d=\"M73 647Q73 657 77 670T89 683Q90 683 161 688T234 694Q246 694 246 685T212 542Q204 508 195 472T180 418L176 399Q176 396 182 402Q231 442 283 442Q345 442 383 396T422 280Q422 169 343 79T173 -11Q123 -11 82 27T40 150V159Q40 180 48 217T97 414Q147 611 147 623T109 637Q104 637 101 637H96Q86 637 83 637T76 640T73 647ZM336 325V331Q336 405 275 405Q258 405 240 397T207 376T181 352T163 330L157 322L136 236Q114 150 114 114Q114 66 138 42Q154 26 178 26Q211 26 245 58Q270 81 285 114T318 219Q336 291 336 325Z\"></path></g><g data-mml-node=\"mo\" transform=\"translate(3180.8,0)\"><path data-c=\"2B\" d=\"M56 237T56 250T70 270H369V420L370 570Q380 583 389 583Q402 583 409 568V270H707Q722 262 722 250T707 230H409V-68Q401 -82 391 -82H389H387Q375 -82 369 -68V230H70Q56 237 56 250Z\"></path></g><g data-mml-node=\"mn\" transform=\"translate(4181,0)\"><path data-c=\"31\" d=\"M213 578L200 573Q186 568 160 563T102 556H83V602H102Q149 604 189 617T245 641T273 663Q275 666 285 666Q294 666 302 660V361L303 61Q310 54 315 52T339 48T401 46H427V0H416Q395 3 257 3Q121 3 100 0H88V46H114Q136 46 152 46T177 47T193 50T201 52T207 57T213 61V578Z\"></path></g><g data-mml-node=\"mo\" transform=\"translate(4681,0)\"><path data-c=\"29\" d=\"M60 749L64 750Q69 750 74 750H86L114 726Q208 641 251 514T294 250Q294 182 284 119T261 12T224 -76T186 -143T145 -194T113 -227T90 -246Q87 -249 86 -250H74Q66 -250 63 -250T58 -247T55 -238Q56 -237 66 -225Q221 -64 221 250T66 725Q56 737 55 738Q55 746 60 749Z\"></path></g><g data-mml-node=\"mo\" transform=\"translate(5070,0)\"><path data-c=\"2309\" d=\"M21 717T21 730T32 746T75 750H147H256Q266 742 269 735V-235Q262 -248 251 -250Q247 -250 244 -249T239 -247T235 -244T233 -241T231 -237T229 -234V710H133Q119 710 99 710T71 709Q43 709 32 713Z\"></path></g></g></g></g></svg></mjx-container><br><mjx-container class=\"MathJax\" jax=\"SVG\"><svg style=\"vertical-align: -0.566ex\" xmlns=\"http://www.w3.org/2000/svg\" width=\"20.749ex\" height=\"2.262ex\" role=\"img\" focusable=\"false\" viewBox=\"0 -750 9171.1 1000\"><g stroke=\"currentColor\" fill=\"currentColor\" stroke-width=\"0\" transform=\"scale(1,-1)\"><g data-mml-node=\"math\"><g data-mml-node=\"mi\"><text data-variant=\"italic\" transform=\"scale(1,-1)\" font-size=\"884px\" font-family=\"serif\" font-style=\"italic\">时</text></g><g data-mml-node=\"mi\" transform=\"translate(900,0)\"><text data-variant=\"italic\" transform=\"scale(1,-1)\" font-size=\"884px\" font-family=\"serif\" font-style=\"italic\">间</text></g><g data-mml-node=\"mi\" transform=\"translate(1800,0)\"><text data-variant=\"italic\" transform=\"scale(1,-1)\" font-size=\"884px\" font-family=\"serif\" font-style=\"italic\">复</text></g><g data-mml-node=\"mi\" transform=\"translate(2700,0)\"><text data-variant=\"italic\" transform=\"scale(1,-1)\" font-size=\"884px\" font-family=\"serif\" font-style=\"italic\">杂</text></g><g data-mml-node=\"mi\" transform=\"translate(3600,0)\"><text data-variant=\"italic\" transform=\"scale(1,-1)\" font-size=\"884px\" font-family=\"serif\" font-style=\"italic\">度</text></g><g data-mml-node=\"mo\" transform=\"translate(4777.8,0)\"><path data-c=\"3A\" d=\"M78 370Q78 394 95 412T138 430Q162 430 180 414T199 371Q199 346 182 328T139 310T96 327T78 370ZM78 60Q78 84 95 102T138 120Q162 120 180 104T199 61Q199 36 182 18T139 0T96 17T78 60Z\"></path></g><g data-mml-node=\"mi\" transform=\"translate(5333.6,0)\"><path data-c=\"1D442\" d=\"M740 435Q740 320 676 213T511 42T304 -22Q207 -22 138 35T51 201Q50 209 50 244Q50 346 98 438T227 601Q351 704 476 704Q514 704 524 703Q621 689 680 617T740 435ZM637 476Q637 565 591 615T476 665Q396 665 322 605Q242 542 200 428T157 216Q157 126 200 73T314 19Q404 19 485 98T608 313Q637 408 637 476Z\"></path></g><g data-mml-node=\"mi\" transform=\"translate(6096.6,0)\"><path data-c=\"1D459\" d=\"M117 59Q117 26 142 26Q179 26 205 131Q211 151 215 152Q217 153 225 153H229Q238 153 241 153T246 151T248 144Q247 138 245 128T234 90T214 43T183 6T137 -11Q101 -11 70 11T38 85Q38 97 39 102L104 360Q167 615 167 623Q167 626 166 628T162 632T157 634T149 635T141 636T132 637T122 637Q112 637 109 637T101 638T95 641T94 647Q94 649 96 661Q101 680 107 682T179 688Q194 689 213 690T243 693T254 694Q266 694 266 686Q266 675 193 386T118 83Q118 81 118 75T117 65V59Z\"></path></g><g data-mml-node=\"mi\" transform=\"translate(6394.6,0)\"><path data-c=\"1D45C\" d=\"M201 -11Q126 -11 80 38T34 156Q34 221 64 279T146 380Q222 441 301 441Q333 441 341 440Q354 437 367 433T402 417T438 387T464 338T476 268Q476 161 390 75T201 -11ZM121 120Q121 70 147 48T206 26Q250 26 289 58T351 142Q360 163 374 216T388 308Q388 352 370 375Q346 405 306 405Q243 405 195 347Q158 303 140 230T121 120Z\"></path></g><g data-mml-node=\"msub\" transform=\"translate(6879.6,0)\"><g data-mml-node=\"mi\"><path data-c=\"1D454\" d=\"M311 43Q296 30 267 15T206 0Q143 0 105 45T66 160Q66 265 143 353T314 442Q361 442 401 394L404 398Q406 401 409 404T418 412T431 419T447 422Q461 422 470 413T480 394Q480 379 423 152T363 -80Q345 -134 286 -169T151 -205Q10 -205 10 -137Q10 -111 28 -91T74 -71Q89 -71 102 -80T116 -111Q116 -121 114 -130T107 -144T99 -154T92 -162L90 -164H91Q101 -167 151 -167Q189 -167 211 -155Q234 -144 254 -122T282 -75Q288 -56 298 -13Q311 35 311 43ZM384 328L380 339Q377 350 375 354T369 368T359 382T346 393T328 402T306 405Q262 405 221 352Q191 313 171 233T151 117Q151 38 213 38Q269 38 323 108L331 118L384 328Z\"></path></g><g data-mml-node=\"TeXAtom\" transform=\"translate(510,-150) scale(0.707)\" data-mjx-texclass=\"ORD\"><g data-mml-node=\"mn\"><path data-c=\"32\" d=\"M109 429Q82 429 66 447T50 491Q50 562 103 614T235 666Q326 666 387 610T449 465Q449 422 429 383T381 315T301 241Q265 210 201 149L142 93L218 92Q375 92 385 97Q392 99 409 186V189H449V186Q448 183 436 95T421 3V0H50V19V31Q50 38 56 46T86 81Q115 113 136 137Q145 147 170 174T204 211T233 244T261 278T284 308T305 340T320 369T333 401T340 431T343 464Q343 527 309 573T212 619Q179 619 154 602T119 569T109 550Q109 549 114 549Q132 549 151 535T170 489Q170 464 154 447T109 429Z\"></path></g></g></g><g data-mml-node=\"mo\" transform=\"translate(7793.1,0)\"><path data-c=\"28\" d=\"M94 250Q94 319 104 381T127 488T164 576T202 643T244 695T277 729T302 750H315H319Q333 750 333 741Q333 738 316 720T275 667T226 581T184 443T167 250T184 58T225 -81T274 -167T316 -220T333 -241Q333 -250 318 -250H315H302L274 -226Q180 -141 137 -14T94 250Z\"></path></g><g data-mml-node=\"mi\" transform=\"translate(8182.1,0)\"><path data-c=\"1D45B\" d=\"M21 287Q22 293 24 303T36 341T56 388T89 425T135 442Q171 442 195 424T225 390T231 369Q231 367 232 367L243 378Q304 442 382 442Q436 442 469 415T503 336T465 179T427 52Q427 26 444 26Q450 26 453 27Q482 32 505 65T540 145Q542 153 560 153Q580 153 580 145Q580 144 576 130Q568 101 554 73T508 17T439 -10Q392 -10 371 17T350 73Q350 92 386 193T423 345Q423 404 379 404H374Q288 404 229 303L222 291L189 157Q156 26 151 16Q138 -11 108 -11Q95 -11 87 -5T76 7T74 17Q74 30 112 180T152 343Q153 348 153 366Q153 405 129 405Q91 405 66 305Q60 285 60 284Q58 278 41 278H27Q21 284 21 287Z\"></path></g><g data-mml-node=\"mo\" transform=\"translate(8782.1,0)\"><path data-c=\"29\" d=\"M60 749L64 750Q69 750 74 750H86L114 726Q208 641 251 514T294 250Q294 182 284 119T261 12T224 -76T186 -143T145 -194T113 -227T90 -246Q87 -249 86 -250H74Q66 -250 63 -250T58 -247T55 -238Q56 -237 66 -225Q221 -64 221 250T66 725Q56 737 55 738Q55 746 60 749Z\"></path></g></g></g></svg></mjx-container></li>\n<li>代码实现</li>\n</ul></blockquote>\n<pre class=\"line-numbers language-cpp\" data-language=\"cpp\"><code class=\"language-cpp\"><span class=\"token macro property\"><span class=\"token directive-hash\">#</span><span class=\"token directive keyword\">include</span><span class=\"token string\">&lt;bits/stdc++.h&gt;</span></span>\n\n<span class=\"token keyword\">typedef</span> <span class=\"token keyword\">long</span> <span class=\"token keyword\">long</span> ll<span class=\"token punctuation\">;</span>\n<span class=\"token keyword\">typedef</span> <span class=\"token keyword\">unsigned</span> <span class=\"token keyword\">long</span> <span class=\"token keyword\">long</span> ull<span class=\"token punctuation\">;</span>\n\n<span class=\"token keyword\">const</span> <span class=\"token keyword\">int</span> N <span class=\"token operator\">=</span> <span class=\"token number\">1e5</span><span class=\"token operator\">+</span><span class=\"token number\">10</span><span class=\"token punctuation\">,</span>M <span class=\"token operator\">=</span> N<span class=\"token punctuation\">,</span>INF <span class=\"token operator\">=</span> <span class=\"token number\">0x3f3f3f3f</span><span class=\"token punctuation\">,</span>P <span class=\"token operator\">=</span> <span class=\"token number\">998244353</span><span class=\"token punctuation\">;</span>\n\n\n<span class=\"token keyword\">int</span> <span class=\"token function\">main</span><span class=\"token punctuation\">(</span><span class=\"token punctuation\">)</span>\n<span class=\"token punctuation\">{</span>\n    std<span class=\"token double-colon punctuation\">::</span>ios<span class=\"token double-colon punctuation\">::</span><span class=\"token function\">sync_with_stdio</span><span class=\"token punctuation\">(</span><span class=\"token boolean\">false</span><span class=\"token punctuation\">)</span><span class=\"token punctuation\">;</span>\n    ll a<span class=\"token punctuation\">,</span>b<span class=\"token punctuation\">,</span>p<span class=\"token punctuation\">;</span>\n    std<span class=\"token double-colon punctuation\">::</span>cin<span class=\"token operator\">&gt;&gt;</span>a<span class=\"token operator\">&gt;&gt;</span>b<span class=\"token operator\">&gt;&gt;</span>p<span class=\"token punctuation\">;</span>\n    ll res <span class=\"token operator\">=</span> <span class=\"token number\">0</span><span class=\"token punctuation\">;</span>\n    <span class=\"token keyword\">for</span><span class=\"token punctuation\">(</span><span class=\"token punctuation\">;</span> b <span class=\"token punctuation\">;</span> b <span class=\"token operator\">&gt;&gt;=</span> <span class=\"token number\">1</span><span class=\"token punctuation\">)</span>\n    <span class=\"token punctuation\">{</span>\n        <span class=\"token keyword\">if</span><span class=\"token punctuation\">(</span>b<span class=\"token operator\">&amp;</span><span class=\"token number\">1</span><span class=\"token punctuation\">)</span>res <span class=\"token operator\">=</span> <span class=\"token punctuation\">(</span>res <span class=\"token operator\">+</span> a<span class=\"token punctuation\">)</span><span class=\"token operator\">%</span>p<span class=\"token punctuation\">;</span>\n        a <span class=\"token operator\">=</span> a <span class=\"token operator\">*</span> <span class=\"token number\">2</span> <span class=\"token operator\">%</span> p<span class=\"token punctuation\">;</span>\n    <span class=\"token punctuation\">}</span>\n    std<span class=\"token double-colon punctuation\">::</span>cout<span class=\"token operator\">&lt;&lt;</span>res<span class=\"token punctuation\">;</span>\n    <span class=\"token keyword\">return</span> <span class=\"token number\">0</span><span class=\"token punctuation\">;</span>\n<span class=\"token punctuation\">}</span><span aria-hidden=\"true\" class=\"line-numbers-rows\"><span></span><span></span><span></span><span></span><span></span><span></span><span></span><span></span><span></span><span></span><span></span><span></span><span></span><span></span><span></span><span></span><span></span><span></span><span></span><span></span><span></span><span></span></span></code></pre>\n<ol>\n<li>思路二<blockquote><span class=\"custom-blockquote-svg\"><svg width=\"24\" height=\"24\" viewBox=\"0 0 24 24\" fill=\"\" xmlns=\"http://www.w3.org/2000/svg\" data-reactroot=\"\">\n<path fill=\"\" d=\"M22 12C22 6.5 17.5 2 12 2C6.5 2 2 6.5 2 12C2 17.5 6.5 22 12 22C13.8 22 15.5 21.5 17 20.6L22 22L20.7 17C21.5 15.5 22 13.8 22 12Z\" undefined=\"1\"></path>\n<path fill=\"\" d=\"M15.97 11.5H16.04C17.12 11.5 18 12.38 18 13.47V13.53C18 14.62 17.12 15.5 16.03 15.5H15.96C14.88 15.5 14 14.62 14 13.53V13.46C14 12.38 14.88 11.5 15.97 11.5Z\" undefined=\"1\"></path>\n<path fill=\"\" d=\"M7.97 11.5H8.04C9.12 11.5 10 12.38 10 13.47V13.53C10 14.62 9.12 15.5 8.03 15.5H7.97C6.88 15.5 6 14.62 6 13.53V13.46C6 12.38 6.88 11.5 7.97 11.5Z\" undefined=\"1\"></path>\n<path stroke-linejoin=\"round\" stroke-linecap=\"round\" stroke-miterlimit=\"10\" stroke-width=\"2\" stroke=\"\" d=\"M17 8.5C15.23 8.97 14.07 10.84 14.01 13.27C14 13.33 14 13.4 14 13.47V13.5\"></path>\n<path stroke-linejoin=\"round\" stroke-linecap=\"round\" stroke-miterlimit=\"10\" stroke-width=\"2\" stroke=\"\" d=\"M9 8.5C7.23 8.97 6.07 10.84 6.01 13.27C6 13.33 6 13.4 6 13.47V13.5\"></path>\n<path stroke-linejoin=\"round\" stroke-linecap=\"round\" stroke-miterlimit=\"10\" stroke-width=\"2\" stroke=\"\" d=\"M15.97 11.5H16.04C17.12 11.5 18 12.38 18 13.47V13.53C18 14.62 17.12 15.5 16.03 15.5H15.96C14.88 15.5 14 14.62 14 13.53V13.46C14 12.38 14.88 11.5 15.97 11.5Z\"></path>\n<path stroke-linejoin=\"round\" stroke-linecap=\"round\" stroke-miterlimit=\"10\" stroke-width=\"2\" stroke=\"\" d=\"M7.97 11.5H8.04C9.12 11.5 10 12.38 10 13.47V13.53C10 14.62 9.12 15.5 8.03 15.5H7.97C6.88 15.5 6 14.62 6 13.53V13.46C6 12.38 6.88 11.5 7.97 11.5Z\"></path>\n</svg>\n</span><p>$利用a<em>b ~mod~p=a</em>b-\\left \\lfloor a<em>b/p \\right \\rfloor</em>p，\\left \\lfloor  \\right \\rfloor为向下取整<mjx-container class=\"MathJax\" jax=\"SVG\"><svg style=\"vertical-align: 0\" xmlns=\"http://www.w3.org/2000/svg\" width=\"0.036ex\" height=\"0.036ex\" role=\"img\" focusable=\"false\" viewBox=\"0 0 16 16\"><g stroke=\"currentColor\" fill=\"currentColor\" stroke-width=\"0\" transform=\"scale(1,-1)\"><g data-mml-node=\"math\"></g></g></svg></mjx-container>首先，假设a&lt;p,b&lt;p,那么a<em>b/p下取整之后一定也小于p，我们可以使用浮点数完成中间计算。<mjx-container class=\"MathJax\" jax=\"SVG\"><svg style=\"vertical-align: 0\" xmlns=\"http://www.w3.org/2000/svg\" width=\"0.036ex\" height=\"0.036ex\" role=\"img\" focusable=\"false\" viewBox=\"0 0 16 16\"><g stroke=\"currentColor\" fill=\"currentColor\" stroke-width=\"0\" transform=\"scale(1,-1)\"><g data-mml-node=\"math\"></g></g></svg></mjx-container>long~double的浮点数有效数字在18<mjx-container class=\"MathJax\" jax=\"SVG\"><svg style=\"vertical-align: 0\" xmlns=\"http://www.w3.org/2000/svg\" width=\"0.566ex\" height=\"0.036ex\" role=\"img\" focusable=\"false\" viewBox=\"0 0 250 16\"><g stroke=\"currentColor\" fill=\"currentColor\" stroke-width=\"0\" transform=\"scale(1,-1)\"><g data-mml-node=\"math\"><g data-mml-node=\"mtext\"><path data-c=\"A0\" d=\"\"></path></g></g></g></svg></mjx-container>19位之间，可以胜任。<mjx-container class=\"MathJax\" jax=\"SVG\"><svg style=\"vertical-align: 0\" xmlns=\"http://www.w3.org/2000/svg\" width=\"0.036ex\" height=\"0.036ex\" role=\"img\" focusable=\"false\" viewBox=\"0 0 16 16\"><g stroke=\"currentColor\" fill=\"currentColor\" stroke-width=\"0\" transform=\"scale(1,-1)\"><g data-mml-node=\"math\"></g></g></svg></mjx-container>a</em>b 和\\left \\lfloor a<em>b/p \\right \\rfloor</em>p可能会很大,但是易知它们的差值一定在0<mjx-container class=\"MathJax\" jax=\"SVG\"><svg style=\"vertical-align: 0\" xmlns=\"http://www.w3.org/2000/svg\" width=\"0.566ex\" height=\"0.036ex\" role=\"img\" focusable=\"false\" viewBox=\"0 0 250 16\"><g stroke=\"currentColor\" fill=\"currentColor\" stroke-width=\"0\" transform=\"scale(1,-1)\"><g data-mml-node=\"math\"><g data-mml-node=\"mtext\"><path data-c=\"A0\" d=\"\"></path></g></g></g></svg></mjx-container>p-1之间。<mjx-container class=\"MathJax\" jax=\"SVG\"><svg style=\"vertical-align: 0\" xmlns=\"http://www.w3.org/2000/svg\" width=\"0.036ex\" height=\"0.036ex\" role=\"img\" focusable=\"false\" viewBox=\"0 0 16 16\"><g stroke=\"currentColor\" fill=\"currentColor\" stroke-width=\"0\" transform=\"scale(1,-1)\"><g data-mml-node=\"math\"></g></g></svg></mjx-container>因为p的范围在long~long以内，所以只需要关心a<em>b 和\\left \\lfloor a</em>b/p \\right \\rfloor*p在long~long范围内的位，更高的位一定是相同的。$</p></blockquote>\n</li>\n</ol>\n<ul>\n<li><p>时间复杂度分析</p>\n<blockquote><span class=\"custom-blockquote-svg\"><svg width=\"24\" height=\"24\" viewBox=\"0 0 24 24\" fill=\"\" xmlns=\"http://www.w3.org/2000/svg\" data-reactroot=\"\">\n<path fill=\"\" d=\"M22 12C22 6.5 17.5 2 12 2C6.5 2 2 6.5 2 12C2 17.5 6.5 22 12 22C13.8 22 15.5 21.5 17 20.6L22 22L20.7 17C21.5 15.5 22 13.8 22 12Z\" undefined=\"1\"></path>\n<path fill=\"\" d=\"M15.97 11.5H16.04C17.12 11.5 18 12.38 18 13.47V13.53C18 14.62 17.12 15.5 16.03 15.5H15.96C14.88 15.5 14 14.62 14 13.53V13.46C14 12.38 14.88 11.5 15.97 11.5Z\" undefined=\"1\"></path>\n<path fill=\"\" d=\"M7.97 11.5H8.04C9.12 11.5 10 12.38 10 13.47V13.53C10 14.62 9.12 15.5 8.03 15.5H7.97C6.88 15.5 6 14.62 6 13.53V13.46C6 12.38 6.88 11.5 7.97 11.5Z\" undefined=\"1\"></path>\n<path stroke-linejoin=\"round\" stroke-linecap=\"round\" stroke-miterlimit=\"10\" stroke-width=\"2\" stroke=\"\" d=\"M17 8.5C15.23 8.97 14.07 10.84 14.01 13.27C14 13.33 14 13.4 14 13.47V13.5\"></path>\n<path stroke-linejoin=\"round\" stroke-linecap=\"round\" stroke-miterlimit=\"10\" stroke-width=\"2\" stroke=\"\" d=\"M9 8.5C7.23 8.97 6.07 10.84 6.01 13.27C6 13.33 6 13.4 6 13.47V13.5\"></path>\n<path stroke-linejoin=\"round\" stroke-linecap=\"round\" stroke-miterlimit=\"10\" stroke-width=\"2\" stroke=\"\" d=\"M15.97 11.5H16.04C17.12 11.5 18 12.38 18 13.47V13.53C18 14.62 17.12 15.5 16.03 15.5H15.96C14.88 15.5 14 14.62 14 13.53V13.46C14 12.38 14.88 11.5 15.97 11.5Z\"></path>\n<path stroke-linejoin=\"round\" stroke-linecap=\"round\" stroke-miterlimit=\"10\" stroke-width=\"2\" stroke=\"\" d=\"M7.97 11.5H8.04C9.12 11.5 10 12.38 10 13.47V13.53C10 14.62 9.12 15.5 8.03 15.5H7.97C6.88 15.5 6 14.62 6 13.53V13.46C6 12.38 6.88 11.5 7.97 11.5Z\"></path>\n</svg>\n</span><p><mjx-container class=\"MathJax\" jax=\"SVG\"><svg style=\"vertical-align: -0.566ex\" xmlns=\"http://www.w3.org/2000/svg\" width=\"4.618ex\" height=\"2.262ex\" role=\"img\" focusable=\"false\" viewBox=\"0 -750 2041 1000\"><g stroke=\"currentColor\" fill=\"currentColor\" stroke-width=\"0\" transform=\"scale(1,-1)\"><g data-mml-node=\"math\"><g data-mml-node=\"mi\"><path data-c=\"1D442\" d=\"M740 435Q740 320 676 213T511 42T304 -22Q207 -22 138 35T51 201Q50 209 50 244Q50 346 98 438T227 601Q351 704 476 704Q514 704 524 703Q621 689 680 617T740 435ZM637 476Q637 565 591 615T476 665Q396 665 322 605Q242 542 200 428T157 216Q157 126 200 73T314 19Q404 19 485 98T608 313Q637 408 637 476Z\"></path></g><g data-mml-node=\"mo\" transform=\"translate(763,0)\"><path data-c=\"28\" d=\"M94 250Q94 319 104 381T127 488T164 576T202 643T244 695T277 729T302 750H315H319Q333 750 333 741Q333 738 316 720T275 667T226 581T184 443T167 250T184 58T225 -81T274 -167T316 -220T333 -241Q333 -250 318 -250H315H302L274 -226Q180 -141 137 -14T94 250Z\"></path></g><g data-mml-node=\"mn\" transform=\"translate(1152,0)\"><path data-c=\"31\" d=\"M213 578L200 573Q186 568 160 563T102 556H83V602H102Q149 604 189 617T245 641T273 663Q275 666 285 666Q294 666 302 660V361L303 61Q310 54 315 52T339 48T401 46H427V0H416Q395 3 257 3Q121 3 100 0H88V46H114Q136 46 152 46T177 47T193 50T201 52T207 57T213 61V578Z\"></path></g><g data-mml-node=\"mo\" transform=\"translate(1652,0)\"><path data-c=\"29\" d=\"M60 749L64 750Q69 750 74 750H86L114 726Q208 641 251 514T294 250Q294 182 284 119T261 12T224 -76T186 -143T145 -194T113 -227T90 -246Q87 -249 86 -250H74Q66 -250 63 -250T58 -247T55 -238Q56 -237 66 -225Q221 -64 221 250T66 725Q56 737 55 738Q55 746 60 749Z\"></path></g></g></g></svg></mjx-container></p></blockquote>\n</li>\n<li><p>代码实现</p>\n</li>\n</ul>\n<pre class=\"line-numbers language-cpp\" data-language=\"cpp\"><code class=\"language-cpp\"><span class=\"token macro property\"><span class=\"token directive-hash\">#</span><span class=\"token directive keyword\">include</span><span class=\"token string\">&lt;bits/stdc++.h&gt;</span></span>\n\n<span class=\"token keyword\">typedef</span> <span class=\"token keyword\">long</span> <span class=\"token keyword\">long</span> ll<span class=\"token punctuation\">;</span>\n<span class=\"token keyword\">typedef</span> <span class=\"token keyword\">unsigned</span> <span class=\"token keyword\">long</span> <span class=\"token keyword\">long</span> ull<span class=\"token punctuation\">;</span>\n\n<span class=\"token keyword\">const</span> <span class=\"token keyword\">int</span> N <span class=\"token operator\">=</span> <span class=\"token number\">1e5</span><span class=\"token operator\">+</span><span class=\"token number\">10</span><span class=\"token punctuation\">,</span>M <span class=\"token operator\">=</span> N<span class=\"token punctuation\">,</span>INF <span class=\"token operator\">=</span> <span class=\"token number\">0x3f3f3f3f</span><span class=\"token punctuation\">,</span>P <span class=\"token operator\">=</span> <span class=\"token number\">998244353</span><span class=\"token punctuation\">;</span>\n\n\n<span class=\"token keyword\">int</span> <span class=\"token function\">main</span><span class=\"token punctuation\">(</span><span class=\"token punctuation\">)</span>\n<span class=\"token punctuation\">{</span>\n    std<span class=\"token double-colon punctuation\">::</span>ios<span class=\"token double-colon punctuation\">::</span><span class=\"token function\">sync_with_stdio</span><span class=\"token punctuation\">(</span><span class=\"token boolean\">false</span><span class=\"token punctuation\">)</span><span class=\"token punctuation\">;</span>\n    ll a<span class=\"token punctuation\">,</span>b<span class=\"token punctuation\">,</span>p<span class=\"token punctuation\">;</span>\n    std<span class=\"token double-colon punctuation\">::</span>cin<span class=\"token operator\">&gt;&gt;</span>a<span class=\"token operator\">&gt;&gt;</span>b<span class=\"token operator\">&gt;&gt;</span>p<span class=\"token punctuation\">;</span>\n    a <span class=\"token operator\">%=</span> p<span class=\"token punctuation\">,</span>b <span class=\"token operator\">%=</span> p<span class=\"token punctuation\">;</span>\n    ll c <span class=\"token operator\">=</span> <span class=\"token punctuation\">(</span><span class=\"token keyword\">long</span> <span class=\"token keyword\">double</span><span class=\"token punctuation\">)</span>a <span class=\"token operator\">*</span> b <span class=\"token operator\">/</span> p<span class=\"token punctuation\">;</span>\n    ll res <span class=\"token operator\">=</span> a <span class=\"token operator\">*</span> b <span class=\"token operator\">-</span> c <span class=\"token operator\">*</span> p<span class=\"token punctuation\">;</span>\n    <span class=\"token keyword\">if</span><span class=\"token punctuation\">(</span>res <span class=\"token operator\">&lt;</span> <span class=\"token number\">0</span><span class=\"token punctuation\">)</span>res <span class=\"token operator\">+=</span> p<span class=\"token punctuation\">;</span>\n    <span class=\"token keyword\">else</span> <span class=\"token keyword\">if</span><span class=\"token punctuation\">(</span>res <span class=\"token operator\">&gt;=</span> p<span class=\"token punctuation\">)</span>res <span class=\"token operator\">-=</span> p<span class=\"token punctuation\">;</span>\n    std<span class=\"token double-colon punctuation\">::</span>cout<span class=\"token operator\">&lt;&lt;</span>res<span class=\"token punctuation\">;</span>\n    <span class=\"token keyword\">return</span> <span class=\"token number\">0</span><span class=\"token punctuation\">;</span>\n<span class=\"token punctuation\">}</span><span aria-hidden=\"true\" class=\"line-numbers-rows\"><span></span><span></span><span></span><span></span><span></span><span></span><span></span><span></span><span></span><span></span><span></span><span></span><span></span><span></span><span></span><span></span><span></span><span></span><span></span><span></span><span></span></span></code></pre>\n<ul>\n<li>注意点</li>\n</ul>\n<ol>\n<li>为什么a和b要mod p？<br> 因为我们需要保证<mjx-container class=\"MathJax\" jax=\"SVG\"><svg style=\"vertical-align: -0.566ex\" xmlns=\"http://www.w3.org/2000/svg\" width=\"6.573ex\" height=\"2.262ex\" role=\"img\" focusable=\"false\" viewBox=\"0 -750 2905.4 1000\"><g stroke=\"currentColor\" fill=\"currentColor\" stroke-width=\"0\" transform=\"scale(1,-1)\"><g data-mml-node=\"math\"><g data-mml-node=\"mi\"><path data-c=\"1D44E\" d=\"M33 157Q33 258 109 349T280 441Q331 441 370 392Q386 422 416 422Q429 422 439 414T449 394Q449 381 412 234T374 68Q374 43 381 35T402 26Q411 27 422 35Q443 55 463 131Q469 151 473 152Q475 153 483 153H487Q506 153 506 144Q506 138 501 117T481 63T449 13Q436 0 417 -8Q409 -10 393 -10Q359 -10 336 5T306 36L300 51Q299 52 296 50Q294 48 292 46Q233 -10 172 -10Q117 -10 75 30T33 157ZM351 328Q351 334 346 350T323 385T277 405Q242 405 210 374T160 293Q131 214 119 129Q119 126 119 118T118 106Q118 61 136 44T179 26Q217 26 254 59T298 110Q300 114 325 217T351 328Z\"></path></g><g data-mml-node=\"mo\" transform=\"translate(751.2,0)\"><path data-c=\"2217\" d=\"M229 286Q216 420 216 436Q216 454 240 464Q241 464 245 464T251 465Q263 464 273 456T283 436Q283 419 277 356T270 286L328 328Q384 369 389 372T399 375Q412 375 423 365T435 338Q435 325 425 315Q420 312 357 282T289 250L355 219L425 184Q434 175 434 161Q434 146 425 136T401 125Q393 125 383 131T328 171L270 213Q283 79 283 63Q283 53 276 44T250 35Q231 35 224 44T216 63Q216 80 222 143T229 213L171 171Q115 130 110 127Q106 124 100 124Q87 124 76 134T64 161Q64 166 64 169T67 175T72 181T81 188T94 195T113 204T138 215T170 230T210 250L74 315Q65 324 65 338Q65 353 74 363T98 374Q106 374 116 368T171 328L229 286Z\"></path></g><g data-mml-node=\"mi\" transform=\"translate(1473.4,0)\"><path data-c=\"1D44F\" d=\"M73 647Q73 657 77 670T89 683Q90 683 161 688T234 694Q246 694 246 685T212 542Q204 508 195 472T180 418L176 399Q176 396 182 402Q231 442 283 442Q345 442 383 396T422 280Q422 169 343 79T173 -11Q123 -11 82 27T40 150V159Q40 180 48 217T97 414Q147 611 147 623T109 637Q104 637 101 637H96Q86 637 83 637T76 640T73 647ZM336 325V331Q336 405 275 405Q258 405 240 397T207 376T181 352T163 330L157 322L136 236Q114 150 114 114Q114 66 138 42Q154 26 178 26Q211 26 245 58Q270 81 285 114T318 219Q336 291 336 325Z\"></path></g><g data-mml-node=\"TeXAtom\" data-mjx-texclass=\"ORD\" transform=\"translate(1902.4,0)\"><g data-mml-node=\"mo\"><path data-c=\"2F\" d=\"M423 750Q432 750 438 744T444 730Q444 725 271 248T92 -240Q85 -250 75 -250Q68 -250 62 -245T56 -231Q56 -221 230 257T407 740Q411 750 423 750Z\"></path></g></g><g data-mml-node=\"mi\" transform=\"translate(2402.4,0)\"><path data-c=\"1D45D\" d=\"M23 287Q24 290 25 295T30 317T40 348T55 381T75 411T101 433T134 442Q209 442 230 378L240 387Q302 442 358 442Q423 442 460 395T497 281Q497 173 421 82T249 -10Q227 -10 210 -4Q199 1 187 11T168 28L161 36Q160 35 139 -51T118 -138Q118 -144 126 -145T163 -148H188Q194 -155 194 -157T191 -175Q188 -187 185 -190T172 -194Q170 -194 161 -194T127 -193T65 -192Q-5 -192 -24 -194H-32Q-39 -187 -39 -183Q-37 -156 -26 -148H-6Q28 -147 33 -136Q36 -130 94 103T155 350Q156 355 156 364Q156 405 131 405Q109 405 94 377T71 316T59 280Q57 278 43 278H29Q23 284 23 287ZM178 102Q200 26 252 26Q282 26 310 49T356 107Q374 141 392 215T411 325V331Q411 405 350 405Q339 405 328 402T306 393T286 380T269 365T254 350T243 336T235 326L232 322Q232 321 229 308T218 264T204 212Q178 106 178 102Z\"></path></g></g></g></svg></mjx-container>范围在long long内</li>\n<li>为什么用别的浮点数类型(double)会错？<br> 因为double的有效位数过小，在乘p以后导致错误<br> 例子：0.002 <em> 10000和0.0018 </em> 10000显然不同<br> 精度足够以后：<br> 0.0018 <em> 10000 和0.001811 </em> 10000不会影响</li>\n<li>为什么最后要有这一段代码？</li>\n</ol>\n<pre class=\"line-numbers language-cpp\" data-language=\"cpp\"><code class=\"language-cpp\"><span class=\"token keyword\">if</span><span class=\"token punctuation\">(</span>res <span class=\"token operator\">&lt;</span> <span class=\"token number\">0</span><span class=\"token punctuation\">)</span>res <span class=\"token operator\">+=</span> p<span class=\"token punctuation\">;</span>\n<span class=\"token keyword\">else</span> <span class=\"token keyword\">if</span><span class=\"token punctuation\">(</span>res <span class=\"token operator\">&gt;=</span> p<span class=\"token punctuation\">)</span>res <span class=\"token operator\">-=</span> p<span class=\"token punctuation\">;</span><span aria-hidden=\"true\" class=\"line-numbers-rows\"><span></span><span></span></span></code></pre>\n<p>因为在第一行对a和b mod p后，由模的性质可以知道最后答案可能会与原来的答案产生p的差值。</p>\n<ul>\n<li>题目：<br><a href=\"https://www.acwing.com/problem/content/92/\">64位整数乘法</a></li>\n</ul>\n","text":"0x01 位运算——64位整数乘法 问题简析 C++内置的最高整数类型是64位，所以显然不能通过直接运算得到答案，我们需要一些特殊的处理方法，在这里提供两种方法。 思路一 类似于快速幂的思想，把b拆分成k位二进制。$b=C_{k-1}2^{k-1}+C_{k-2}2^{k-2}…...","link":"","photos":[],"count_time":{"symbolsCount":"1.8k","symbolsTime":"2 mins."},"categories":[],"tags":[],"toc":"<ol class=\"toc\"><li class=\"toc-item toc-level-2\"><a class=\"toc-link\" href=\"#0x01-%E4%BD%8D%E8%BF%90%E7%AE%97%E2%80%94%E2%80%9464%E4%BD%8D%E6%95%B4%E6%95%B0%E4%B9%98%E6%B3%95\"><span class=\"toc-text\">0x01 位运算——64位整数乘法</span></a></li></ol>","author":{"name":"skynesser","slug":"blog-author","avatar":"https://img-blog.csdnimg.cn/20210313122054101.png","link":"/","description":"","socials":{"github":"","twitter":"","stackoverflow":"","wechat":"","qq":"","weibo":"","zhihu":"","csdn":"","juejin":"","customs":{}}},"mapped":true,"prev_post":{"title":"0x01位运算--最短Hamilton路径","uid":"5e6fa880a2b85943c805a5daeb5a1a2c","slug":"0x01位运算-最短Hamilton路径","date":"2022-04-14T04:59:38.000Z","updated":"2022-04-14T05:11:49.611Z","comments":true,"path":"api/articles/0x01位运算-最短Hamilton路径.json","keywords":null,"cover":[],"text":"0x01位运算——最短Hamilton路径 说明 本题的正解——状态压缩dp，我们将在0x56节详细介绍 思路分析 我们可以使用一个**n维的bool数组**记录下某时刻经过了哪些点，未经过哪些点，而这里的**n维的bool数组**，可以用一个n位的二进制数代替。 在这个二进制数...","link":"","photos":[],"count_time":{"symbolsCount":"1.1k","symbolsTime":"1 mins."},"categories":[],"tags":[],"author":{"name":"skynesser","slug":"blog-author","avatar":"https://img-blog.csdnimg.cn/20210313122054101.png","link":"/","description":"","socials":{"github":"","twitter":"","stackoverflow":"","wechat":"","qq":"","weibo":"","zhihu":"","csdn":"","juejin":"","customs":{}}}},"next_post":{"title":"0x01位运算--a^b","uid":"2fe208e266b9d06ce4fcbff1033f1615","slug":"0x01位运算-a-b","date":"2022-04-14T04:57:50.000Z","updated":"2022-04-14T05:11:58.900Z","comments":true,"path":"api/articles/0x01位运算-a-b.json","keywords":null,"cover":[],"text":"0x01位运算——a^b 题目： 思路分析 如果在二进制下有位每一位为可以将分解为：$b=C_{k-1}2^{k-1}+C_{k-2}2^{k-2}+…+C_{0}*2^{0}因为2^{k-1}=(2^{k-2})^{2},所以很容易用递推求出每一个乘积项$ 时间复杂度分析 ，所...","link":"","photos":[],"count_time":{"symbolsCount":723,"symbolsTime":"1 mins."},"categories":[],"tags":[],"author":{"name":"skynesser","slug":"blog-author","avatar":"https://img-blog.csdnimg.cn/20210313122054101.png","link":"/","description":"","socials":{"github":"","twitter":"","stackoverflow":"","wechat":"","qq":"","weibo":"","zhihu":"","csdn":"","juejin":"","customs":{}}}}}